mysql_yang_mcp/__init__.py
mysql_yang_mcp/__main__.py
mysql_yang_mcp/mysql_server.py
mysql_yang_mcp-0.1.0.dist-info/LICENSE
mysql_yang_mcp-0.1.0.dist-info/METADATA
mysql_yang_mcp-0.1.0.dist-info/WHEEL
mysql_yang_mcp-0.1.0.dist-info/entry_points.txt
mysql_yang_mcp-0.1.0.dist-info/top_level.txt
mysql_yang_mcp-0.1.0.dist-info/RECORD
