Metadata-Version: 2.1
Name: mysql_yang_mcp
Version: 0.1.0
Summary: A MySQL query tool with MCP support
Home-page: https://github.com/jokulyang/mytool
Author: jokul
Author-email: test@qq.com
Classifier: Programming Language :: Python :: 3
Classifier: License :: OSI Approved :: MIT License
Classifier: Operating System :: OS Independent
Classifier: Development Status :: 3 - Alpha
Classifier: Intended Audience :: Developers
Classifier: Topic :: Database :: Database Engines/Servers
Classifier: Topic :: Software Development :: Libraries :: Python Modules
Requires-Python: >=3.11
License-File: LICENSE
Requires-Dist: mcp>=1.9.0
Requires-Dist: pydantic>=2.0.0
Requires-Dist: mysql-connector-python>=8.0.0
Requires-Dist: python-dotenv>=0.19.0
Requires-Dist: typing-extensions>=4.7.0
